{
    "status": "quick-out", 
    "tag_sheets": [], 
    "clone_priviledge": "none", 
    "flash_project_settings": {}, 
    "id": "071c5453-f675-44c4-8517-79c569afd920", 
    "size": "", 
    "by_user": "greg.connell.mbp-dev", 
    "name": "bt-ES6-Webpack-Intro-Endframe-Branded", 
    "modified_datetime": "05/16/18 10:12am", 
    "check_logs": [
        {
            "action": "quick-out", 
            "log_datetime": "05/16/18 10:12am", 
            "size_hash": "d41d8cd98f00b204e9800998ecf8427e", 
            "by_user": "greg.connell.mbp-dev", 
            "comments": ""
        }
    ], 
    "html_deploy_profiles": [], 
    "is_being_processed": false, 
    "mirror_priviledge": "", 
    "type": "CreativeIteration"
}